elastic_panel/__init__.py
elastic_panel/panel.py
elastic_panel/static/elastic_panel/js/elastic_panel.js
elastic_panel/templates/elastic_panel/elastic_panel.html
tests/__init__.py
tests/test_toolbar.py
django_elasticsearch_debug_toolbar-3.0.2.dist-info/AUTHORS
django_elasticsearch_debug_toolbar-3.0.2.dist-info/LICENSE
django_elasticsearch_debug_toolbar-3.0.2.dist-info/METADATA
django_elasticsearch_debug_toolbar-3.0.2.dist-info/WHEEL
django_elasticsearch_debug_toolbar-3.0.2.dist-info/top_level.txt
django_elasticsearch_debug_toolbar-3.0.2.dist-info/RECORD
