Metadata-Version: 2.1
Name: django-elasticsearch-debug-toolbar
Version: 3.0.2
Summary: A Django Debug Toolbar panel for Elasticsearch
Home-page: http://github.com/Benoss/django-elasticsearch-debug-toolbar
Author: Benoit Chabord
Author-email: benauf@gmail.com
License: MIT
Keywords: django,es,elastic,elasticsearch
Platform: UNKNOWN
Classifier: Framework :: Django
Classifier: Intended Audience :: Developers
Classifier: License :: OSI Approved :: MIT License
Classifier: Operating System :: OS Independent
Classifier: Programming Language :: Python
Classifier: Programming Language :: Python :: 3.8
Classifier: Programming Language :: Python :: 3.9
Classifier: Programming Language :: Python :: 3.10
License-File: LICENSE
License-File: AUTHORS
